model_sketch_book/Concept.py
model_sketch_book/Dataset.py
model_sketch_book/README.md
model_sketch_book/Result.py
model_sketch_book/Sketch.py
model_sketch_book/SketchBook.py
model_sketch_book/__init__.py
model_sketch_book/helper_functions.py
model_sketch_book/model_sketch_book.py
model_sketch_book/msb_enums.py
model_sketch_book/msb_stateless.py
model_sketch_book-1.0.2.dist-info/LICENSE
model_sketch_book-1.0.2.dist-info/METADATA
model_sketch_book-1.0.2.dist-info/WHEEL
model_sketch_book-1.0.2.dist-info/RECORD
